core/__init__.py
core/output_manager.py
core/pdf_handler.py
core/pipeline_processor.py
detection/__init__.py
detection/column_detector.py
detection/figure_detector.py
detection/table_detector.py
detection/text_detector.py
extraction/__init__.py
extraction/content_extractor.py
extraction/mistral_service.py
processing/__init__.py
processing/caption_processor.py
processing/content_organizer.py
quanta/__init__.py
quanta/cli.py
quanta/types.py
quanta_pdf-1.0.3.dist-info/licenses/LICENSE
utils/__init__.py
utils/ml_models.py
quanta_pdf-1.0.3.dist-info/METADATA
quanta_pdf-1.0.3.dist-info/WHEEL
quanta_pdf-1.0.3.dist-info/entry_points.txt
quanta_pdf-1.0.3.dist-info/top_level.txt
quanta_pdf-1.0.3.dist-info/RECORD
