Metadata-Version: 2.4
Name: quanta-pdf
Version: 1.0.3
Summary: Advanced PDF layout analysis engine for extracting figures, tables, and structured content
Author-email: Sovit Nayak <sovitnayak1258@gmail.com>, Manush Murali <manush@example.com>
Maintainer-email: Sovit Nayak <sovitnayak1258@gmail.com>, Manush Murali <manush@example.com>
License: MIT
Project-URL: Homepage, https://github.com/Magnet-AI/Quanta
Project-URL: Documentation, https://quanta.readthedocs.io
Project-URL: Repository, https://github.com/Magnet-AI/Quanta.git
Project-URL: Bug Tracker, https://github.com/Magnet-AI/Quanta/issues
Project-URL: Changelog, https://github.com/Magnet-AI/Quanta/blob/main/CHANGELOG.md
Keywords: pdf,layout-analysis,computer-vision,document-processing,figure-extraction,table-detection,ocr,machine-learning
Classifier: Development Status :: 4 - Beta
Classifier: Intended Audience :: Developers
Classifier: Intended Audience :: Science/Research
Classifier: License :: OSI Approved :: MIT License
Classifier: Operating System :: OS Independent
Classifier: Programming Language :: Python :: 3
Classifier: Programming Language :: Python :: 3.8
Classifier: Programming Language :: Python :: 3.9
Classifier: Programming Language :: Python :: 3.10
Classifier: Programming Language :: Python :: 3.11
Classifier: Programming Language :: Python :: 3.12
Classifier: Topic :: Scientific/Engineering :: Artificial Intelligence
Classifier: Topic :: Scientific/Engineering :: Image Processing
Classifier: Topic :: Text Processing :: Markup
Classifier: Topic :: Multimedia :: Graphics :: Graphics Conversion
Requires-Python: >=3.8
License-File: LICENSE
Requires-Dist: opencv-python>=4.8.0
Requires-Dist: PyMuPDF>=1.23.0
Requires-Dist: numpy>=1.21.0
Requires-Dist: scikit-learn>=1.0.0
Requires-Dist: Pillow>=9.0.0
Requires-Dist: pandas>=1.3.0
Requires-Dist: matplotlib>=3.5.0
Provides-Extra: dev
Requires-Dist: pytest>=7.0.0; extra == "dev"
Requires-Dist: pytest-cov>=4.0.0; extra == "dev"
Requires-Dist: black>=22.0.0; extra == "dev"
Requires-Dist: flake8>=5.0.0; extra == "dev"
Requires-Dist: mypy>=1.0.0; extra == "dev"
Requires-Dist: pre-commit>=2.20.0; extra == "dev"
Provides-Extra: docs
Requires-Dist: sphinx>=5.0.0; extra == "docs"
Requires-Dist: sphinx-rtd-theme>=1.0.0; extra == "docs"
Requires-Dist: myst-parser>=0.18.0; extra == "docs"
Provides-Extra: test
Requires-Dist: pytest>=7.0.0; extra == "test"
Requires-Dist: pytest-cov>=4.0.0; extra == "test"
Requires-Dist: pytest-xdist>=3.0.0; extra == "test"
Dynamic: license-file
